unidist/__init__.py
unidist/_version.py
unidist/api.py
unidist/config/__init__.py
unidist/config/parameter.py
unidist/config/backends/__init__.py
unidist/config/backends/common/__init__.py
unidist/config/backends/common/envvars.py
unidist/config/backends/dask/__init__.py
unidist/config/backends/dask/envvars.py
unidist/config/backends/mpi/__init__.py
unidist/config/backends/mpi/envvars.py
unidist/config/backends/ray/__init__.py
unidist/config/backends/ray/envvars.py
unidist/core/__init__.py
unidist/core/backends/__init__.py
unidist/core/backends/common/__init__.py
unidist/core/backends/common/data_id.py
unidist/core/backends/common/utils.py
unidist/core/backends/dask/__init__.py
unidist/core/backends/dask/actor.py
unidist/core/backends/dask/backend.py
unidist/core/backends/dask/remote_function.py
unidist/core/backends/dask/utils.py
unidist/core/backends/mpi/__init__.py
unidist/core/backends/mpi/actor.py
unidist/core/backends/mpi/backend.py
unidist/core/backends/mpi/remote_function.py
unidist/core/backends/mpi/utils.py
unidist/core/backends/mpi/core/__init__.py
unidist/core/backends/mpi/core/_memory.cp312-win32.pyd
unidist/core/backends/mpi/core/async_operations.py
unidist/core/backends/mpi/core/common.py
unidist/core/backends/mpi/core/communication.py
unidist/core/backends/mpi/core/local_object_store.py
unidist/core/backends/mpi/core/object_store.py
unidist/core/backends/mpi/core/serialization.py
unidist/core/backends/mpi/core/shared_object_store.py
unidist/core/backends/mpi/core/controller/__init__.py
unidist/core/backends/mpi/core/controller/actor.py
unidist/core/backends/mpi/core/controller/api.py
unidist/core/backends/mpi/core/controller/common.py
unidist/core/backends/mpi/core/controller/garbage_collector.py
unidist/core/backends/mpi/core/monitor/__init__.py
unidist/core/backends/mpi/core/monitor/loop.py
unidist/core/backends/mpi/core/monitor/shared_memory_manager.py
unidist/core/backends/mpi/core/worker/__init__.py
unidist/core/backends/mpi/core/worker/loop.py
unidist-0.7.2.dist-info/AUTHORS
unidist-0.7.2.dist-info/LICENSE
unidist-0.7.2.dist-info/METADATA
unidist-0.7.2.dist-info/WHEEL
unidist-0.7.2.dist-info/top_level.txt
unidist-0.7.2.dist-info/RECORD
