Metadata-Version: 2.1
Name: unidist
Version: 0.7.2
Summary: Unified Distributed Execution
Home-page: https://github.com/modin-project/unidist
License: Apache-2.0
Requires-Python: >=3.9
License-File: LICENSE
License-File: AUTHORS
Requires-Dist: packaging
Requires-Dist: cloudpickle
Provides-Extra: all
Requires-Dist: ray[default]>=1.13.0; extra == "all"
Requires-Dist: pydantic<2; extra == "all"
Requires-Dist: dask[complete]>=2.22.0; extra == "all"
Requires-Dist: distributed>=2.22.0; extra == "all"
Requires-Dist: mpi4py>=3.0.3; extra == "all"
Requires-Dist: msgpack>=1.0.0; extra == "all"
Requires-Dist: psutil; extra == "all"
Provides-Extra: dask
Requires-Dist: dask[complete]>=2.22.0; extra == "dask"
Requires-Dist: distributed>=2.22.0; extra == "dask"
Provides-Extra: mpi
Requires-Dist: mpi4py>=3.0.3; extra == "mpi"
Requires-Dist: msgpack>=1.0.0; extra == "mpi"
Requires-Dist: psutil; extra == "mpi"
Provides-Extra: ray
Requires-Dist: ray[default]>=1.13.0; extra == "ray"
Requires-Dist: pydantic<2; extra == "ray"
